dj_experiment
