Metadata-Version: 1.1
Name: dj-experiment
Version: 0.3.1
Summary: Django application for organizing numerical model experiment output
Home-page: https://github.com/francbartoli/dj-experiment
Author: Francesco Bartoli
Author-email: francesco.bartoli@geobeyond.it
License: MIT
Keywords: dj-experiment
Platform: UNKNOWN
Classifier: Development Status :: 3 - Alpha
Classifier: Framework :: Django
Classifier: Framework :: Django :: 1.8
Classifier: Framework :: Django :: 1.9
Classifier: Framework :: Django :: 1.10
Classifier: Intended Audience :: Developers
Classifier: License :: OSI Approved :: BSD License
Classifier: Natural Language :: English
Classifier: Programming Language :: Python :: 2
Classifier: Programming Language :: Python :: 2.7
Classifier: Programming Language :: Python :: 3
Classifier: Programming Language :: Python :: 3.3
Classifier: Programming Language :: Python :: 3.4
Classifier: Programming Language :: Python :: 3.5
